bioviper/__init__.py
bioviper/hmmer_tools.py
bioviper/msa.py
bioviper/pdb.py
bioviper/phylo.py
bioviper-0.2.1.dist-info/LICENSE
bioviper-0.2.1.dist-info/METADATA
bioviper-0.2.1.dist-info/WHEEL
bioviper-0.2.1.dist-info/top_level.txt
bioviper-0.2.1.dist-info/RECORD
