Metadata-Version: 2.1
Name: bioviper
Version: 0.2.1
Summary: Enhancements to Biopython for working with biological data
Author: Sam Berry
Author-email: Sam Berry <sberry@g.harvard.edu>
License: MIT License
Project-URL: Homepage, https://github.com/samberry19/bioviper
Project-URL: Bug Tracker, https://github.com/samberry19/bioviper/issues
Classifier: Programming Language :: Python :: 3
Classifier: License :: OSI Approved :: MIT License
Classifier: Operating System :: OS Independent
Requires-Python: >=3.7
License-File: LICENSE
Requires-Dist: numpy
Requires-Dist: pandas
Requires-Dist: matplotlib
Requires-Dist: biopython
Requires-Dist: tqdm
Requires-Dist: ete3
